cryptosnake/__init__.py
cryptosnake/snake.py
cryptosnake-0.1.3.dist-info/LICENSE
cryptosnake-0.1.3.dist-info/METADATA
cryptosnake-0.1.3.dist-info/WHEEL
cryptosnake-0.1.3.dist-info/top_level.txt
cryptosnake-0.1.3.dist-info/RECORD
