Metadata-Version: 2.1
Name: cryptosnake
Version: 0.1.3
Summary: Simple crypto data API
Home-page: https://github.com/reppon97/cryptosnake
Author: Rejep Mammedov
Author-email: reppon97@gmail.com
License: MIT
Platform: UNKNOWN
Classifier: License :: OSI Approved :: MIT License
Requires-Dist: requests
